pqdm/__init__.py
pqdm/_base.py
pqdm/constants.py
pqdm/processes.py
pqdm/threads.py
pqdm/utils.py
pqdm-0.2.0.dist-info/AUTHORS.rst
pqdm-0.2.0.dist-info/LICENSE
pqdm-0.2.0.dist-info/METADATA
pqdm-0.2.0.dist-info/WHEEL
pqdm-0.2.0.dist-info/top_level.txt
pqdm-0.2.0.dist-info/RECORD
