Metadata-Version: 2.1
Name: pqdm
Version: 0.2.0
Summary: PQDM is a TQDM and concurrent futures wrapper to allow enjoyable paralellization of progress bars.
Home-page: https://github.com/niedakh/pqdm
Author: Piotr Szymański
Author-email: niedakh@gmail.com
License: MIT license
Keywords: pqdm
Platform: UNKNOWN
Classifier: Development Status :: 2 - Pre-Alpha
Classifier: Intended Audience :: Developers
Classifier: License :: OSI Approved :: MIT License
Classifier: Natural Language :: English
Classifier: Programming Language :: Python :: 3
Classifier: Programming Language :: Python :: 3.6
Classifier: Programming Language :: Python :: 3.7
Classifier: Programming Language :: Python :: 3.8
Classifier: Programming Language :: Python :: 3.9
Requires-Python: >=3.6
